flexy/__init__.py
flexy-0.1.1.dist-info/LICENSE
flexy-0.1.1.dist-info/METADATA
flexy-0.1.1.dist-info/WHEEL
flexy-0.1.1.dist-info/top_level.txt
flexy-0.1.1.dist-info/RECORD
