Metadata-Version: 2.1
Name: flexy
Version: 0.1.1
Summary: Flexible YAML loader.
Author-email: Sun Yijiang <sunyijiang@gmail.com>
Project-URL: Homepage, https://github.com/sunyj/flexy
Project-URL: Bug Tracker, https://github.com/sunyj/flexy/issues
Classifier: Programming Language :: Python :: 3
Classifier: License :: OSI Approved :: MIT License
Classifier: Operating System :: OS Independent
Requires-Python: >=3.4
License-File: LICENSE
Requires-Dist: revo
Requires-Dist: pyyaml
